{
  "assetId": "KR:006400",
  "symbol": "006400",
  "universeId": "KOSPI_SAMPLE",
  "source": "Yahoo Finance via yfinance",
  "sourceTier": "personal_fallback",
  "warnings": [
    "unofficial",
    "personal_use_only"
  ],
  "updatedAt": "2026-06-17T21:47:25.957452",
  "dataStatus": "cached",
  "bars": [
    {
      "assetId": "KR:006400",
      "date": "2025-12-17",
      "open": 296000.0,
      "high": 297000.0,
      "low": 291500.0,
      "close": 295000.0,
      "volume": 232155.0
    },
    {
      "assetId": "KR:006400",
      "date": "2025-12-18",
      "open": 285000.0,
      "high": 285500.0,
      "low": 277000.0,
      "close": 277000.0,
      "volume": 644420.0
    },
    {
      "assetId": "KR:006400",
      "date": "2025-12-19",
      "open": 280000.0,
      "high": 280000.0,
      "low": 267500.0,
      "close": 279500.0,
      "volume": 691283.0
    },
    {
      "assetId": "KR:006400",
      "date": "2025-12-22",
      "open": 282000.0,
      "high": 285000.0,
      "low": 277500.0,
      "close": 282500.0,
      "volume": 311296.0
    },
    {
      "assetId": "KR:006400",
      "date": "2025-12-23",
      "open": 283000.0,
      "high": 283000.0,
      "low": 277750.0,
      "close": 279500.0,
      "volume": 329038.0
    },
    {
      "assetId": "KR:006400",
      "date": "2025-12-24",
      "open": 281500.0,
      "high": 283500.0,
      "low": 278500.0,
      "close": 280000.0,
      "volume": 206418.0
    },
    {
      "assetId": "KR:006400",
      "date": "2025-12-26",
      "open": 280000.0,
      "high": 282500.0,
      "low": 273000.0,
      "close": 274000.0,
      "volume": 340872.0
    },
    {
      "assetId": "KR:006400",
      "date": "2025-12-29",
      "open": 267000.0,
      "high": 278500.0,
      "low": 265000.0,
      "close": 277500.0,
      "volume": 330047.0
    },
    {
      "assetId": "KR:006400",
      "date": "2025-12-30",
      "open": 273500.0,
      "high": 275000.0,
      "low": 267000.0,
      "close": 269500.0,
      "volume": 448385.0
    },
    {
      "assetId": "KR:006400",
      "date": "2026-01-02",
      "open": 268000.0,
      "high": 268000.0,
      "low": 259000.0,
      "close": 262500.0,
      "volume": 616243.0
    },
    {
      "assetId": "KR:006400",
      "date": "2026-01-05",
      "open": 260000.0,
      "high": 280000.0,
      "low": 259500.0,
      "close": 275000.0,
      "volume": 805956.0
    },
    {
      "assetId": "KR:006400",
      "date": "2026-01-06",
      "open": 282000.0,
      "high": 282000.0,
      "low": 274000.0,
      "close": 277000.0,
      "volume": 448991.0
    },
    {
      "assetId": "KR:006400",
      "date": "2026-01-07",
      "open": 279000.0,
      "high": 280000.0,
      "low": 268500.0,
      "close": 270500.0,
      "volume": 603479.0
    },
    {
      "assetId": "KR:006400",
      "date": "2026-01-08",
      "open": 271500.0,
      "high": 274000.0,
      "low": 269000.0,
      "close": 271000.0,
      "volume": 556265.0
    },
    {
      "assetId": "KR:006400",
      "date": "2026-01-09",
      "open": 272000.0,
      "high": 272000.0,
      "low": 265250.0,
      "close": 267500.0,
      "volume": 433710.0
    },
    {
      "assetId": "KR:006400",
      "date": "2026-01-12",
      "open": 265500.0,
      "high": 280500.0,
      "low": 264000.0,
      "close": 278000.0,
      "volume": 704473.0
    },
    {
      "assetId": "KR:006400",
      "date": "2026-01-13",
      "open": 281500.0,
      "high": 302500.0,
      "low": 276000.0,
      "close": 300000.0,
      "volume": 1248744.0
    },
    {
      "assetId": "KR:006400",
      "date": "2026-01-14",
      "open": 298500.0,
      "high": 298500.0,
      "low": 284500.0,
      "close": 285500.0,
      "volume": 663816.0
    },
    {
      "assetId": "KR:006400",
      "date": "2026-01-15",
      "open": 287000.0,
      "high": 292000.0,
      "low": 284250.0,
      "close": 291500.0,
      "volume": 487778.0
    },
    {
      "assetId": "KR:006400",
      "date": "2026-01-16",
      "open": 291500.0,
      "high": 292000.0,
      "low": 286000.0,
      "close": 289000.0,
      "volume": 447796.0
    },
    {
      "assetId": "KR:006400",
      "date": "2026-01-19",
      "open": 289000.0,
      "high": 320000.0,
      "low": 286000.0,
      "close": 314000.0,
      "volume": 1430872.0
    },
    {
      "assetId": "KR:006400",
      "date": "2026-01-20",
      "open": 319000.0,
      "high": 339500.0,
      "low": 315500.0,
      "close": 326000.0,
      "volume": 2148250.0
    },
    {
      "assetId": "KR:006400",
      "date": "2026-01-21",
      "open": 316000.0,
      "high": 326500.0,
      "low": 310000.0,
      "close": 324000.0,
      "volume": 1109366.0
    },
    {
      "assetId": "KR:006400",
      "date": "2026-01-22",
      "open": 333000.0,
      "high": 385500.0,
      "low": 325500.0,
      "close": 384500.0,
      "volume": 5826300.0
    },
    {
      "assetId": "KR:006400",
      "date": "2026-01-23",
      "open": 402000.0,
      "high": 402000.0,
      "low": 362500.0,
      "close": 373000.0,
      "volume": 3366383.0
    },
    {
      "assetId": "KR:006400",
      "date": "2026-01-26",
      "open": 385500.0,
      "high": 389500.0,
      "low": 375500.0,
      "close": 387000.0,
      "volume": 1609025.0
    },
    {
      "assetId": "KR:006400",
      "date": "2026-01-27",
      "open": 373500.0,
      "high": 398000.0,
      "low": 367500.0,
      "close": 387500.0,
      "volume": 1845095.0
    },
    {
      "assetId": "KR:006400",
      "date": "2026-01-28",
      "open": 394000.0,
      "high": 411500.0,
      "low": 390000.0,
      "close": 396500.0,
      "volume": 2071072.0
    },
    {
      "assetId": "KR:006400",
      "date": "2026-01-29",
      "open": 397500.0,
      "high": 399500.0,
      "low": 376500.0,
      "close": 388000.0,
      "volume": 1317541.0
    },
    {
      "assetId": "KR:006400",
      "date": "2026-01-30",
      "open": 390500.0,
      "high": 400500.0,
      "low": 376000.0,
      "close": 390000.0,
      "volume": 1730887.0
    },
    {
      "assetId": "KR:006400",
      "date": "2026-02-02",
      "open": 380000.0,
      "high": 386500.0,
      "low": 355500.0,
      "close": 356000.0,
      "volume": 1586089.0
    },
    {
      "assetId": "KR:006400",
      "date": "2026-02-03",
      "open": 366500.0,
      "high": 381000.0,
      "low": 357500.0,
      "close": 374500.0,
      "volume": 930111.0
    },
    {
      "assetId": "KR:006400",
      "date": "2026-02-04",
      "open": 374000.0,
      "high": 396000.0,
      "low": 372500.0,
      "close": 391500.0,
      "volume": 1224216.0
    },
    {
      "assetId": "KR:006400",
      "date": "2026-02-05",
      "open": 388000.0,
      "high": 399500.0,
      "low": 380000.0,
      "close": 385500.0,
      "volume": 1150046.0
    },
    {
      "assetId": "KR:006400",
      "date": "2026-02-06",
      "open": 370500.0,
      "high": 373000.0,
      "low": 358500.0,
      "close": 370000.0,
      "volume": 727300.0
    },
    {
      "assetId": "KR:006400",
      "date": "2026-02-09",
      "open": 381500.0,
      "high": 383000.0,
      "low": 375000.0,
      "close": 380000.0,
      "volume": 477549.0
    },
    {
      "assetId": "KR:006400",
      "date": "2026-02-10",
      "open": 385500.0,
      "high": 391500.0,
      "low": 377000.0,
      "close": 381000.0,
      "volume": 504263.0
    },
    {
      "assetId": "KR:006400",
      "date": "2026-02-11",
      "open": 381500.0,
      "high": 384500.0,
      "low": 373500.0,
      "close": 377000.0,
      "volume": 367852.0
    },
    {
      "assetId": "KR:006400",
      "date": "2026-02-12",
      "open": 381000.0,
      "high": 386000.0,
      "low": 373000.0,
      "close": 385500.0,
      "volume": 639928.0
    },
    {
      "assetId": "KR:006400",
      "date": "2026-02-13",
      "open": 377500.0,
      "high": 383000.0,
      "low": 372500.0,
      "close": 374500.0,
      "volume": 517002.0
    },
    {
      "assetId": "KR:006400",
      "date": "2026-02-19",
      "open": 379500.0,
      "high": 409000.0,
      "low": 377000.0,
      "close": 408000.0,
      "volume": 1085467.0
    },
    {
      "assetId": "KR:006400",
      "date": "2026-02-20",
      "open": 402000.0,
      "high": 420500.0,
      "low": 399000.0,
      "close": 402000.0,
      "volume": 928083.0
    },
    {
      "assetId": "KR:006400",
      "date": "2026-02-23",
      "open": 407500.0,
      "high": 407500.0,
      "low": 387000.0,
      "close": 391500.0,
      "volume": 793713.0
    },
    {
      "assetId": "KR:006400",
      "date": "2026-02-24",
      "open": 400500.0,
      "high": 427000.0,
      "low": 399500.0,
      "close": 421500.0,
      "volume": 2584055.0
    },
    {
      "assetId": "KR:006400",
      "date": "2026-02-25",
      "open": 422000.0,
      "high": 443500.0,
      "low": 415000.0,
      "close": 433000.0,
      "volume": 1253279.0
    },
    {
      "assetId": "KR:006400",
      "date": "2026-02-26",
      "open": 439500.0,
      "high": 457000.0,
      "low": 436500.0,
      "close": 449000.0,
      "volume": 1109842.0
    },
    {
      "assetId": "KR:006400",
      "date": "2026-02-27",
      "open": 439500.0,
      "high": 473500.0,
      "low": 438500.0,
      "close": 466000.0,
      "volume": 1207350.0
    },
    {
      "assetId": "KR:006400",
      "date": "2026-03-03",
      "open": 453500.0,
      "high": 454500.0,
      "low": 408000.0,
      "close": 408000.0,
      "volume": 1453235.0
    },
    {
      "assetId": "KR:006400",
      "date": "2026-03-04",
      "open": 390000.0,
      "high": 406000.0,
      "low": 348500.0,
      "close": 351000.0,
      "volume": 1895549.0
    },
    {
      "assetId": "KR:006400",
      "date": "2026-03-05",
      "open": 391000.0,
      "high": 407000.0,
      "low": 385000.0,
      "close": 392500.0,
      "volume": 1008865.0
    },
    {
      "assetId": "KR:006400",
      "date": "2026-03-06",
      "open": 388500.0,
      "high": 411500.0,
      "low": 385500.0,
      "close": 410500.0,
      "volume": 796681.0
    },
    {
      "assetId": "KR:006400",
      "date": "2026-03-09",
      "open": 386500.0,
      "high": 394500.0,
      "low": 375500.0,
      "close": 389000.0,
      "volume": 754807.0
    },
    {
      "assetId": "KR:006400",
      "date": "2026-03-10",
      "open": 415000.0,
      "high": 415000.0,
      "low": 394000.0,
      "close": 403500.0,
      "volume": 597355.0
    },
    {
      "assetId": "KR:006400",
      "date": "2026-03-11",
      "open": 413500.0,
      "high": 419000.0,
      "low": 394500.0,
      "close": 400000.0,
      "volume": 531148.0
    },
    {
      "assetId": "KR:006400",
      "date": "2026-03-12",
      "open": 396000.0,
      "high": 402000.0,
      "low": 394000.0,
      "close": 400000.0,
      "volume": 616460.0
    },
    {
      "assetId": "KR:006400",
      "date": "2026-03-13",
      "open": 387000.0,
      "high": 397000.0,
      "low": 384500.0,
      "close": 388000.0,
      "volume": 531172.0
    },
    {
      "assetId": "KR:006400",
      "date": "2026-03-16",
      "open": 395000.0,
      "high": 398000.0,
      "low": 380000.0,
      "close": 383000.0,
      "volume": 483616.0
    },
    {
      "assetId": "KR:006400",
      "date": "2026-03-17",
      "open": 395000.0,
      "high": 397500.0,
      "low": 388000.0,
      "close": 389000.0,
      "volume": 359325.0
    },
    {
      "assetId": "KR:006400",
      "date": "2026-03-18",
      "open": 397000.0,
      "high": 405000.0,
      "low": 393500.0,
      "close": 405000.0,
      "volume": 384421.0
    },
    {
      "assetId": "KR:006400",
      "date": "2026-03-19",
      "open": 397000.0,
      "high": 414000.0,
      "low": 396000.0,
      "close": 402500.0,
      "volume": 428488.0
    },
    {
      "assetId": "KR:006400",
      "date": "2026-03-20",
      "open": 405000.0,
      "high": 407000.0,
      "low": 398000.0,
      "close": 400500.0,
      "volume": 397940.0
    },
    {
      "assetId": "KR:006400",
      "date": "2026-03-23",
      "open": 386500.0,
      "high": 387000.0,
      "low": 375500.0,
      "close": 376500.0,
      "volume": 462325.0
    },
    {
      "assetId": "KR:006400",
      "date": "2026-03-24",
      "open": 392000.0,
      "high": 403000.0,
      "low": 383500.0,
      "close": 397500.0,
      "volume": 531265.0
    },
    {
      "assetId": "KR:006400",
      "date": "2026-03-25",
      "open": 401000.0,
      "high": 411500.0,
      "low": 399500.0,
      "close": 404000.0,
      "volume": 416484.0
    },
    {
      "assetId": "KR:006400",
      "date": "2026-03-26",
      "open": 402000.0,
      "high": 413500.0,
      "low": 391000.0,
      "close": 396500.0,
      "volume": 455967.0
    },
    {
      "assetId": "KR:006400",
      "date": "2026-03-27",
      "open": 387500.0,
      "high": 409000.0,
      "low": 375000.0,
      "close": 396500.0,
      "volume": 657568.0
    },
    {
      "assetId": "KR:006400",
      "date": "2026-03-30",
      "open": 389000.0,
      "high": 418000.0,
      "low": 388500.0,
      "close": 412500.0,
      "volume": 735298.0
    },
    {
      "assetId": "KR:006400",
      "date": "2026-03-31",
      "open": 419500.0,
      "high": 429500.0,
      "low": 404000.0,
      "close": 408000.0,
      "volume": 1110671.0
    },
    {
      "assetId": "KR:006400",
      "date": "2026-04-01",
      "open": 425000.0,
      "high": 434000.0,
      "low": 413000.0,
      "close": 432000.0,
      "volume": 779644.0
    },
    {
      "assetId": "KR:006400",
      "date": "2026-04-02",
      "open": 434500.0,
      "high": 460000.0,
      "low": 430000.0,
      "close": 443000.0,
      "volume": 1822137.0
    },
    {
      "assetId": "KR:006400",
      "date": "2026-04-03",
      "open": 451500.0,
      "high": 460000.0,
      "low": 432500.0,
      "close": 438500.0,
      "volume": 692098.0
    },
    {
      "assetId": "KR:006400",
      "date": "2026-04-06",
      "open": 441000.0,
      "high": 470000.0,
      "low": 438000.0,
      "close": 453500.0,
      "volume": 1125434.0
    },
    {
      "assetId": "KR:006400",
      "date": "2026-04-07",
      "open": 448500.0,
      "high": 468500.0,
      "low": 445000.0,
      "close": 456500.0,
      "volume": 759485.0
    },
    {
      "assetId": "KR:006400",
      "date": "2026-04-08",
      "open": 471000.0,
      "high": 471500.0,
      "low": 454500.0,
      "close": 471500.0,
      "volume": 821542.0
    },
    {
      "assetId": "KR:006400",
      "date": "2026-04-09",
      "open": 475000.0,
      "high": 493500.0,
      "low": 469000.0,
      "close": 480000.0,
      "volume": 1003279.0
    },
    {
      "assetId": "KR:006400",
      "date": "2026-04-10",
      "open": 483000.0,
      "high": 490000.0,
      "low": 473000.0,
      "close": 481000.0,
      "volume": 550626.0
    },
    {
      "assetId": "KR:006400",
      "date": "2026-04-13",
      "open": 476500.0,
      "high": 493000.0,
      "low": 472000.0,
      "close": 477500.0,
      "volume": 482539.0
    },
    {
      "assetId": "KR:006400",
      "date": "2026-04-14",
      "open": 485500.0,
      "high": 491000.0,
      "low": 463000.0,
      "close": 470500.0,
      "volume": 798652.0
    },
    {
      "assetId": "KR:006400",
      "date": "2026-04-15",
      "open": 473500.0,
      "high": 478500.0,
      "low": 466000.0,
      "close": 471000.0,
      "volume": 632770.0
    },
    {
      "assetId": "KR:006400",
      "date": "2026-04-16",
      "open": 473000.0,
      "high": 480000.0,
      "low": 473000.0,
      "close": 478500.0,
      "volume": 357441.0
    },
    {
      "assetId": "KR:006400",
      "date": "2026-04-17",
      "open": 480000.0,
      "high": 515000.0,
      "low": 473000.0,
      "close": 513000.0,
      "volume": 1116580.0
    },
    {
      "assetId": "KR:006400",
      "date": "2026-04-20",
      "open": 515000.0,
      "high": 549000.0,
      "low": 509000.0,
      "close": 538000.0,
      "volume": 827022.0
    },
    {
      "assetId": "KR:006400",
      "date": "2026-04-21",
      "open": 570000.0,
      "high": 648000.0,
      "low": 557000.0,
      "close": 645000.0,
      "volume": 2533682.0
    },
    {
      "assetId": "KR:006400",
      "date": "2026-04-22",
      "open": 686000.0,
      "high": 686000.0,
      "low": 647000.0,
      "close": 659000.0,
      "volume": 1727542.0
    },
    {
      "assetId": "KR:006400",
      "date": "2026-04-23",
      "open": 657000.0,
      "high": 669000.0,
      "low": 613000.0,
      "close": 630000.0,
      "volume": 1204489.0
    },
    {
      "assetId": "KR:006400",
      "date": "2026-04-24",
      "open": 648000.0,
      "high": 663000.0,
      "low": 631000.0,
      "close": 641000.0,
      "volume": 786062.0
    },
    {
      "assetId": "KR:006400",
      "date": "2026-04-27",
      "open": 641000.0,
      "high": 648000.0,
      "low": 616000.0,
      "close": 635000.0,
      "volume": 701082.0
    },
    {
      "assetId": "KR:006400",
      "date": "2026-04-28",
      "open": 657000.0,
      "high": 690000.0,
      "low": 650000.0,
      "close": 680000.0,
      "volume": 1454459.0
    },
    {
      "assetId": "KR:006400",
      "date": "2026-04-29",
      "open": 689000.0,
      "high": 714000.0,
      "low": 685000.0,
      "close": 712000.0,
      "volume": 1268312.0
    },
    {
      "assetId": "KR:006400",
      "date": "2026-04-30",
      "open": 721000.0,
      "high": 723000.0,
      "low": 692000.0,
      "close": 695000.0,
      "volume": 853824.0
    },
    {
      "assetId": "KR:006400",
      "date": "2026-05-04",
      "open": 715000.0,
      "high": 717000.0,
      "low": 694000.0,
      "close": 705000.0,
      "volume": 663957.0
    },
    {
      "assetId": "KR:006400",
      "date": "2026-05-06",
      "open": 707000.0,
      "high": 707000.0,
      "low": 677000.0,
      "close": 698000.0,
      "volume": 813564.0
    },
    {
      "assetId": "KR:006400",
      "date": "2026-05-07",
      "open": 698000.0,
      "high": 698000.0,
      "low": 677000.0,
      "close": 694000.0,
      "volume": 604589.0
    },
    {
      "assetId": "KR:006400",
      "date": "2026-05-08",
      "open": 683000.0,
      "high": 694000.0,
      "low": 671000.0,
      "close": 678000.0,
      "volume": 460537.0
    },
    {
      "assetId": "KR:006400",
      "date": "2026-05-11",
      "open": 670000.0,
      "high": 693000.0,
      "low": 651000.0,
      "close": 684000.0,
      "volume": 850986.0
    },
    {
      "assetId": "KR:006400",
      "date": "2026-05-12",
      "open": 676000.0,
      "high": 680000.0,
      "low": 616000.0,
      "close": 629000.0,
      "volume": 1349091.0
    },
    {
      "assetId": "KR:006400",
      "date": "2026-05-13",
      "open": 612000.0,
      "high": 645000.0,
      "low": 600000.0,
      "close": 634000.0,
      "volume": 788819.0
    },
    {
      "assetId": "KR:006400",
      "date": "2026-05-14",
      "open": 663000.0,
      "high": 665000.0,
      "low": 623000.0,
      "close": 636000.0,
      "volume": 712838.0
    },
    {
      "assetId": "KR:006400",
      "date": "2026-05-15",
      "open": 629000.0,
      "high": 668000.0,
      "low": 603000.0,
      "close": 614000.0,
      "volume": 1100294.0
    },
    {
      "assetId": "KR:006400",
      "date": "2026-05-18",
      "open": 592000.0,
      "high": 616000.0,
      "low": 565000.0,
      "close": 613000.0,
      "volume": 554836.0
    },
    {
      "assetId": "KR:006400",
      "date": "2026-05-19",
      "open": 612000.0,
      "high": 621000.0,
      "low": 570000.0,
      "close": 587000.0,
      "volume": 511340.0
    },
    {
      "assetId": "KR:006400",
      "date": "2026-05-20",
      "open": 580000.0,
      "high": 584000.0,
      "low": 548000.0,
      "close": 570000.0,
      "volume": 691785.0
    },
    {
      "assetId": "KR:006400",
      "date": "2026-05-21",
      "open": 592000.0,
      "high": 616000.0,
      "low": 578000.0,
      "close": 616000.0,
      "volume": 516899.0
    },
    {
      "assetId": "KR:006400",
      "date": "2026-05-22",
      "open": 640000.0,
      "high": 657000.0,
      "low": 627000.0,
      "close": 647000.0,
      "volume": 652607.0
    },
    {
      "assetId": "KR:006400",
      "date": "2026-05-26",
      "open": 666000.0,
      "high": 667000.0,
      "low": 631000.0,
      "close": 642000.0,
      "volume": 481983.0
    },
    {
      "assetId": "KR:006400",
      "date": "2026-05-27",
      "open": 636000.0,
      "high": 674000.0,
      "low": 629000.0,
      "close": 630000.0,
      "volume": 799920.0
    },
    {
      "assetId": "KR:006400",
      "date": "2026-05-28",
      "open": 660000.0,
      "high": 691000.0,
      "low": 643000.0,
      "close": 676000.0,
      "volume": 1585322.0
    },
    {
      "assetId": "KR:006400",
      "date": "2026-05-29",
      "open": 680000.0,
      "high": 707000.0,
      "low": 657000.0,
      "close": 688000.0,
      "volume": 2040080.0
    },
    {
      "assetId": "KR:006400",
      "date": "2026-06-01",
      "open": 679000.0,
      "high": 679000.0,
      "low": 650000.0,
      "close": 652000.0,
      "volume": 854997.0
    },
    {
      "assetId": "KR:006400",
      "date": "2026-06-02",
      "open": 641000.0,
      "high": 670000.0,
      "low": 595000.0,
      "close": 602000.0,
      "volume": 1018750.0
    },
    {
      "assetId": "KR:006400",
      "date": "2026-06-04",
      "open": 604000.0,
      "high": 624000.0,
      "low": 586000.0,
      "close": 607000.0,
      "volume": 466801.0
    },
    {
      "assetId": "KR:006400",
      "date": "2026-06-05",
      "open": 599000.0,
      "high": 601000.0,
      "low": 555000.0,
      "close": 568000.0,
      "volume": 542951.0
    },
    {
      "assetId": "KR:006400",
      "date": "2026-06-08",
      "open": 504000.0,
      "high": 525000.0,
      "low": 499500.0,
      "close": 503000.0,
      "volume": 624954.0
    },
    {
      "assetId": "KR:006400",
      "date": "2026-06-09",
      "open": 516000.0,
      "high": 527000.0,
      "low": 488000.0,
      "close": 515000.0,
      "volume": 590666.0
    },
    {
      "assetId": "KR:006400",
      "date": "2026-06-10",
      "open": 509000.0,
      "high": 524000.0,
      "low": 482000.0,
      "close": 496500.0,
      "volume": 68.0
    },
    {
      "assetId": "KR:006400",
      "date": "2026-06-11",
      "open": 476500.0,
      "high": 498500.0,
      "low": 466500.0,
      "close": 498500.0,
      "volume": 498703.0
    },
    {
      "assetId": "KR:006400",
      "date": "2026-06-12",
      "open": 531000.0,
      "high": 570000.0,
      "low": 520000.0,
      "close": 539000.0,
      "volume": 677491.0
    },
    {
      "assetId": "KR:006400",
      "date": "2026-06-15",
      "open": 566000.0,
      "high": 573000.0,
      "low": 542000.0,
      "close": 553000.0,
      "volume": 531797.0
    },
    {
      "assetId": "KR:006400",
      "date": "2026-06-16",
      "open": 564000.0,
      "high": 565000.0,
      "low": 546000.0,
      "close": 549000.0,
      "volume": 352915.0
    },
    {
      "assetId": "KR:006400",
      "date": "2026-06-17",
      "open": 556000.0,
      "high": 556000.0,
      "low": 536000.0,
      "close": 550000.0,
      "volume": 277986.0
    }
  ]
}